nsst/__init__.py
nsst/cli.py
nsst-0.3.3.dist-info/METADATA
nsst-0.3.3.dist-info/WHEEL
nsst-0.3.3.dist-info/entry_points.txt
nsst-0.3.3.dist-info/licenses/LICENSE
nsst-0.3.3.dist-info/RECORD
